README.md
setup.py
solarsystem/__init__.py
solarsystem/functions.py
solarsystem/geocentric.py
solarsystem/heliocentric.py
solarsystem/moon.py
solarsystem/sunriseset.py
solarsystem.egg-info/PKG-INFO
solarsystem.egg-info/SOURCES.txt
solarsystem.egg-info/dependency_links.txt
solarsystem.egg-info/top_level.txt