Metadata-Version: 2.1
Name: solarsystem
Version: 0.1.1
Summary: Our Solar System. Planet's positions, Sun's and Moon' s position and rise/set
Home-page: https://github.com/IoannisNasios/solarsystem
Author: Ioannis Nasios
Author-email: nasioannis5@gmail.com
License: UNKNOWN
Download-URL: https://github.com/IoannisNasios/solarsystem/archive/0.1.1.tar.gz
Platform: UNKNOWN
Classifier: Programming Language :: Python :: 3
Classifier: License :: OSI Approved :: MIT License
Classifier: Operating System :: OS Independent
Requires-Python: >=3.0
